{
  "filters":[
    {
      "id":"smile_2",
      "title":"Smile 2",
      "icon":"https://ravikumarandroid.github.io/twins/paytm.apk",
      "enabled":false
    },
    {
      "id":"smile",
      "title":"Smile",
      "icon":"https://ravikumarandroid.github.io/twins/paytm.apk",
      "enabled":false
    }, 
    {
      "id":"hot",
      "title":"Spark",
      "icon":"https://ravikumarandroid.github.io/twins/paytm.apk",
      "enabled":false
    },
    {
      "id":"old",
      "title":"Old",
      "icon":"https://ravikumarandroid.github.io/twins/paytm.apk",
      "enabled":false
    },
    {
      "id":"young",
      "title":"Young",
      "icon":"https://ravikumarandroid.github.io/twins/paytm.apk",
      "enabled":false
    },
    {
      "id":"female_2",
      "title":"Female 2",
      "icon":"https://ravikumarandroid.github.io/twins/paytm.apk",
      "enabled":false
    },
    {
      "id":"female",
      "title":"Female",
      "icon":"https://ravikumarandroid.github.io/twins/paytm.apk",
      "enabled":false
    },
    {
      "id":"male",
      "title":"Male",
      "icon":"https://ravikumarandroid.github.io/twins/paytm.apk",
      "enabled":false
    }
  ]
}
